docs/Makefile
docs/conf.py
docs/index.rst
noggin_messages/__init__.py
noggin_messages/tests/__init__.py
noggin_messages/tests/test_schemas.py
tox.ini
noggin_messages-1.1.0.dist-info/LICENSE
noggin_messages-1.1.0.dist-info/METADATA
noggin_messages-1.1.0.dist-info/WHEEL
noggin_messages-1.1.0.dist-info/entry_points.txt
noggin_messages-1.1.0.dist-info/RECORD
